<soapenv:Envelope xmlns:soapenv="http://schemas.xmlsoap.org/soap/envelope/" xmlns:bfex="http://www.betfair.com/publicapi/v5/BFExchangeService/" xmlns:v5="http://www.betfair.com/publicapi/types/exchange/v5/">
   <soapenv:Header/>
   <soapenv:Body>
      <bfex:placeBetsResponse>
         <bfex:Result>
            <header>
               <errorCode>?</errorCode>
               <minorErrorCode>?</minorErrorCode>
               <sessionToken>?</sessionToken>
               <timestamp>?</timestamp>
            </header>
            <betResults>
               <!--Zero or more repetitions:-->
               <v5:PlaceBetsResult>
                  <averagePriceMatched>?</averagePriceMatched>
                  <betId>?</betId>
                  <resultCode>?</resultCode>
                  <sizeMatched>?</sizeMatched>
                  <success>?</success>
               </v5:PlaceBetsResult>
            </betResults>
            <errorCode>?</errorCode>
            <minorErrorCode>?</minorErrorCode>
         </bfex:Result>
      </bfex:placeBetsResponse>
   </soapenv:Body>
</soapenv:Envelope>