<?xml version="1.0" encoding="UTF-8"?>
<SOAP-ENV:Envelope xmlns:SOAP-ENC="http://schemas.xmlsoap.org/soap/encoding/" xmlns:SOAP-ENV="http://schemas.xmlsoap.org/soap/envelope/" xmlns:xsd="http://www.w3.org/2001/XMLSchema" xmlns:xsi="http://www.w3.org/2001/XMLSchema-instance">
    <SOAP-ENV:Header/>
    <SOAP-ENV:Body xmlns:ns1="http://www.betfair.com/publicapi/v5/BFExchangeService/" xmlns:ns2="http://www.betfair.com/publicapi/types/exchange/v5/">
        <ns1:getMarketTradedVolumeCompressedResponse>
            <ns1:Result>
                <header>
                    <errorCode>OK</errorCode>
                    <minorErrorCode xsi:nil="1"></minorErrorCode>
                    <sessionToken>1018fcdd2ce34ea182aaf2e4df3a0d9c</sessionToken>
                    <timestamp>2013-04-28T14:13:07.006Z</timestamp>
                </header>
                <errorCode>OK</errorCode>
                <tradedVolume>&lt;xsd:element name="tradedVolume" nillable="true"
                    type="xsd:string"/&gt;</tradedVolume>
                <currencyCode>&lt;xsd:element name="currencyCode" nillable="true"
                    type="xsd:string"/&gt;</currencyCode>
                <marketId>0</marketId>
                <minorErrorCode xsi:nil="1"></minorErrorCode>
            </ns1:Result>
        </ns1:getMarketTradedVolumeCompressedResponse>
    </SOAP-ENV:Body>
</SOAP-ENV:Envelope>